setup.py
vk_wall_poster/__init__.py
vk_wall_poster/requester.py
vk_wall_poster/vkposter.py
vk_wall_poster.egg-info/PKG-INFO
vk_wall_poster.egg-info/SOURCES.txt
vk_wall_poster.egg-info/dependency_links.txt
vk_wall_poster.egg-info/requires.txt
vk_wall_poster.egg-info/top_level.txt