Metadata-Version: 1.0
Name: vk-wall-poster
Version: 0.1.0
Summary: Django module for vk wall poster
Home-page: UNKNOWN
Author: Spi4ka
Author-email: UNKNOWN
License: UNKNOWN
Platform: UNKNOWN
